kolibri/__init__.py
kolibri/config.py
kolibri/document.py
kolibri/errors.py
kolibri/init_logger.py
kolibri/kolibri_component.py
kolibri/log.py
kolibri/logger.py
kolibri/metadata.py
kolibri/model_loader.py
kolibri/model_trainer.py
kolibri/modules.py
kolibri/persistor.py
kolibri/pipeline.py
kolibri/sentence.py
kolibri/settings.py
kolibri/test_case.py
kolibri/token.py
kolibri/version.py
kolibri/applications/.DS_Store
kolibri/applications/__init__.py
kolibri/applications/intent_model.py
kolibri/applications/anomaly_detection/__init__.py
kolibri/applications/anomaly_detection/half_space_trees.py
kolibri/applications/anomaly_detection/models.py
kolibri/applications/anomaly_detection/one_class_anomaly_dector.py
kolibri/applications/anomaly_detection/semi_supervised_anomaly_dector.py
kolibri/applications/anomaly_detection/unsupervised_anomaly_dector.py
kolibri/classical/__init__.py
kolibri/classical/tasks/__init__.py
kolibri/classical/tasks/classification/__init__.py
kolibri/classical/tasks/classification/estimator.py
kolibri/classical/tasks/classification/models.py
kolibri/classical/tasks/classification/sklearn_estimator.py
kolibri/classical/tasks/classification/streamed_estimator.py
kolibri/classical/tasks/classification/auto/__init__.py
kolibri/classical/tasks/classification/auto/models.py
kolibri/data/__init__.py
kolibri/data/downloader.py
kolibri/data/ressources.py
kolibri/data/audio/__init__.py
kolibri/data/audio/audio_reader.py
kolibri/data/samplers/__init__.py
kolibri/data/samplers/auto_smpler.py
kolibri/data/text/__init__.py
kolibri/data/text/corpus/__init__.py
kolibri/data/text/corpus/base_stream.py
kolibri/data/text/corpus/corpus.py
kolibri/data/text/corpus/data_stream.py
kolibri/data/text/corpus/file_stream.py
kolibri/data/text/corpus/generators.py
kolibri/data/text/corpus/vocabulary.py
kolibri/data/text/format/__init__.py
kolibri/data/text/format/conll.py
kolibri/data/text/format/csv.py
kolibri/dnn/__init__.py
kolibri/dnn/__version__.py
kolibri/dnn/utils.py
deep_kolibri-0.4.0.dist-info/LICENCE.txt
deep_kolibri-0.4.0.dist-info/METADATA
deep_kolibri-0.4.0.dist-info/WHEEL
deep_kolibri-0.4.0.dist-info/top_level.txt
deep_kolibri-0.4.0.dist-info/RECORD
