Metadata-Version: 2.1
Name: deep-kolibri
Version: 0.4.0
Summary: Deep Learning and more NLP toolkit
Home-page: UNKNOWN
Author: Mohamed Ben Haddou
Author-email: mbenhaddou@mentis.io
License: UNKNOWN
Platform: UNKNOWN
Classifier: Programming Language :: Python :: 3.7
Classifier: Operating System :: OS Independent
Classifier: Development Status :: 4 - Beta
Requires-Python: >=3.7
License-File: LICENCE.txt
Requires-Dist: wheel
Requires-Dist: regex
Requires-Dist: sympy
Requires-Dist: sonopy
Requires-Dist: mlxtend
Requires-Dist: simplejson
Requires-Dist: tensorflow (>=2.0)
Requires-Dist: tensorflow-addons
Requires-Dist: pandas
Requires-Dist: scipy
Requires-Dist: kapre
Requires-Dist: scikit-learn
Requires-Dist: imbalanced-learn
Requires-Dist: sklearn-crfsuite
Requires-Dist: xgboost
Requires-Dist: pygithub
